{
   "files": [    


{
         "name": "SG-001",
         "url": "https://raw.githubusercontent.com/Juessh/Android-VPN/main/Android-TH-001.ovpn"
      },

{
         "name": "SG-002",
         "url": "https://raw.githubusercontent.com/Juessh/Android-VPN/main/Android-TH-002.ovpn"
      },

{
         "name": "TH-001",
         "url": "https://raw.githubusercontent.com/Juessh/Android-VPN/main/Android-TH-003.ovpn"
      },

{
         "name": "TH-002",
         "url": "https://raw.githubusercontent.com/Juessh/Android-VPN/main/Android-TH-004.ovpn"
      },

{
         "name": "TH-003",
         "url": "https://raw.githubusercontent.com/Juessh/Android-VPN/main/Android-TH-005.ovpn"
      },

{
         "name": "TH-004",
         "url": "https://raw.githubusercontent.com/Juessh/Android-VPN/main/Android-TH-006.ovpn"
      }



   ],
"message":"29 August 2022\n\n•Version:1\n\n•✅New Android VPN✅\n\n📢By : JueHtet📢",
   "title":"✅Add New VIP✅" ,
   "version": 1
}



